faster_eth_abi__mypyc.cp314-win32.pyd
faster_eth_abi/__init__.py
faster_eth_abi/_codec.cp314-win32.pyd
faster_eth_abi/_codec.py
faster_eth_abi/_decoding.cp314-win32.pyd
faster_eth_abi/_decoding.py
faster_eth_abi/_encoding.cp314-win32.pyd
faster_eth_abi/_encoding.py
faster_eth_abi/_grammar.cp314-win32.pyd
faster_eth_abi/_grammar.py
faster_eth_abi/abi.cp314-win32.pyd
faster_eth_abi/abi.py
faster_eth_abi/base.py
faster_eth_abi/codec.py
faster_eth_abi/constants.cp314-win32.pyd
faster_eth_abi/constants.py
faster_eth_abi/decoding.py
faster_eth_abi/encoding.py
faster_eth_abi/exceptions.py
faster_eth_abi/from_type_str.cp314-win32.pyd
faster_eth_abi/from_type_str.py
faster_eth_abi/grammar.py
faster_eth_abi/io.py
faster_eth_abi/packed.cp314-win32.pyd
faster_eth_abi/packed.py
faster_eth_abi/py.typed
faster_eth_abi/registry.py
faster_eth_abi/typing.py
faster_eth_abi/tools/__init__.cp314-win32.pyd
faster_eth_abi/tools/__init__.py
faster_eth_abi/tools/_strategies.cp314-win32.pyd
faster_eth_abi/tools/_strategies.py
faster_eth_abi/utils/__init__.cp314-win32.pyd
faster_eth_abi/utils/__init__.py
faster_eth_abi/utils/localcontext.cp314-win32.pyd
faster_eth_abi/utils/localcontext.py
faster_eth_abi/utils/numeric.cp314-win32.pyd
faster_eth_abi/utils/numeric.py
faster_eth_abi/utils/padding.cp314-win32.pyd
faster_eth_abi/utils/padding.py
faster_eth_abi/utils/string.cp314-win32.pyd
faster_eth_abi/utils/string.py
faster_eth_abi/utils/validation.cp314-win32.pyd
faster_eth_abi/utils/validation.py
faster_eth_abi-5.2.23.dist-info/METADATA
faster_eth_abi-5.2.23.dist-info/WHEEL
faster_eth_abi-5.2.23.dist-info/top_level.txt
faster_eth_abi-5.2.23.dist-info/RECORD
