Metadata-Version: 2.1
Name: faster_eth_abi
Version: 5.2.23
Summary: A ~2-6x faster fork of eth_abi: Python utilities for working with Ethereum ABI definitions, especially encoding and decoding. Implemented in C.
Home-page: https://github.com/BobTheBuidler/faster-eth-abi
Author: The Ethereum Foundation
Author-email: snakecharmers@ethereum.org
License: MIT
Project-URL: Documentation, https://eth-abi.readthedocs.io/en/stable/
Project-URL: Release Notes, https://github.com/BobTheBuidler/faster-eth-abi/releases
Project-URL: Issues, https://github.com/BobTheBuidler/faster-eth-abi/issues
Project-URL: Source - Precompiled (.py), https://github.com/BobTheBuidler/faster-eth-utils/tree/master/faster_eth_utils
Project-URL: Source - Compiled (.c), https://github.com/BobTheBuidler/faster-eth-utils/tree/master/build
Project-URL: Benchmarks, https://github.com/BobTheBuidler/faster-eth-utils/tree/master/benchmarks
Project-URL: Benchmarks - Results, https://github.com/BobTheBuidler/faster-eth-utils/tree/master/benchmarks/results
Project-URL: Original, https://github.com/ethereum/eth-abi
Keywords: ethereum
Classifier: Development Status :: 5 - Production/Stable
Classifier: Intended Audience :: Developers
Classifier: License :: OSI Approved :: MIT License
Classifier: Natural Language :: English
Classifier: Programming Language :: Python :: 3
Classifier: Programming Language :: Python :: 3.8
Classifier: Programming Language :: Python :: 3.9
Classifier: Programming Language :: Python :: 3.10
Classifier: Programming Language :: Python :: 3.11
Classifier: Programming Language :: Python :: 3.12
Classifier: Programming Language :: Python :: 3.13
Classifier: Programming Language :: Python :: 3.14
Classifier: Programming Language :: Python :: Implementation :: CPython
Requires-Python: >=3.8, <4
Requires-Dist: cchecksum<0.4,>=0.3.7.dev0
Requires-Dist: faster-eth-utils==5.3.20
Requires-Dist: eth-abi==5.2.0
Requires-Dist: eth-typing==5.2.1
Requires-Dist: mypy-extensions
Requires-Dist: parsimonious<0.11.0,>=0.10.0
Provides-Extra: benchmark
Requires-Dist: pytest>=7.0.0; extra == "benchmark"
Requires-Dist: pytest-codspeed<4.3,>=4.2; extra == "benchmark"
Requires-Dist: pytest-test-groups; extra == "benchmark"
Provides-Extra: codspeed
Requires-Dist: pytest>=7.0.0; extra == "codspeed"
Requires-Dist: pytest-codspeed<4.3,>=4.2; extra == "codspeed"
Requires-Dist: pytest-test-groups; extra == "codspeed"
Provides-Extra: dev
Requires-Dist: mypy<1.18.3,>=1.14.1; extra == "dev"
Requires-Dist: tqdm; extra == "dev"
Requires-Dist: build>=0.9.0; extra == "dev"
Requires-Dist: bump-my-version>=0.19.0; extra == "dev"
Requires-Dist: ipython; extra == "dev"
Requires-Dist: pre-commit>=3.4.0; extra == "dev"
Requires-Dist: tox>=4.0.0; extra == "dev"
Requires-Dist: twine; extra == "dev"
Requires-Dist: wheel; extra == "dev"
Requires-Dist: pytest-benchmark; extra == "dev"
Requires-Dist: sphinx>=6.0.0; extra == "dev"
Requires-Dist: sphinx-autobuild>=2021.3.14; extra == "dev"
Requires-Dist: sphinx-rtd-theme>=1.0.0; extra == "dev"
Requires-Dist: towncrier<26,>=24; extra == "dev"
Requires-Dist: pytest>=7.0.0; extra == "dev"
Requires-Dist: hypothesis<6.108.7,>=6.22.0; extra == "dev"
Requires-Dist: pytest-timeout>=2.0.0; extra == "dev"
Requires-Dist: pytest-xdist>=2.4.0; extra == "dev"
Requires-Dist: pytest-pythonpath>=0.7.1; extra == "dev"
Requires-Dist: eth-hash[pycryptodome]; extra == "dev"
Provides-Extra: docs
Requires-Dist: sphinx>=6.0.0; extra == "docs"
Requires-Dist: sphinx-autobuild>=2021.3.14; extra == "docs"
Requires-Dist: sphinx-rtd-theme>=1.0.0; extra == "docs"
Requires-Dist: towncrier<26,>=24; extra == "docs"
Provides-Extra: mypy
Requires-Dist: mypy<1.18.3,>=1.14.1; extra == "mypy"
Requires-Dist: tqdm; extra == "mypy"
Provides-Extra: test
Requires-Dist: pytest>=7.0.0; extra == "test"
Requires-Dist: hypothesis<6.108.7,>=6.22.0; extra == "test"
Requires-Dist: pytest-timeout>=2.0.0; extra == "test"
Requires-Dist: pytest-xdist>=2.4.0; extra == "test"
Requires-Dist: pytest-pythonpath>=0.7.1; extra == "test"
Requires-Dist: eth-hash[pycryptodome]; extra == "test"
Provides-Extra: tools
Requires-Dist: hypothesis<6.108.7,>=6.22.0; extra == "tools"
